rastafari/__init__.py
rastafari/core.cpython-312-x86_64-linux-musl.so
rastafari/core.pyi
rastafari/py.typed
rastafari2-0.4.1.2.dist-info/METADATA
rastafari2-0.4.1.2.dist-info/top_level.txt
rastafari2-0.4.1.2.dist-info/WHEEL
rastafari2-0.4.1.2.dist-info/RECORD
