Metadata-Version: 2.4
Name: rastafari2
Version: 0.4.1.2
Summary: Rasterize vector features to grids
Home-page: https://git.smhi.se/foclair/rastafari
Author: Eef van Dongen, David Segersson
Author-email: foluftadmin@smhi.se
Project-URL: Bug Tracker, https://git.smhi.se/foclair/rastafari/-/issues
Requires-Python: >=3.9
Requires-Dist: numpy
Requires-Dist: pyproj
Provides-Extra: test
Requires-Dist: mypy; extra == "test"
Requires-Dist: pytest; extra == "test"
Requires-Dist: pytest-cov; extra == "test"
